{
  "job_id": "20260331_160908_1XjV_ot",
  "source_file_id": "1XjVrRp4cZrDw5uVrIG-5tkOdHY8zTWDP",
  "source_file_link": "https://drive.google.com/file/d/1XjVrRp4cZrDw5uVrIG-5tkOdHY8zTWDP/view?usp=drivesdk",
  "published_at": "2026-03-31T07:09:09.709171+00:00",
  "status": "partial_failure",
  "published_docs": [],
  "failures": [
    {
      "category": "deep_report",
      "error": "Missing REQUIRED markdown for deep_report in /Users/kk/Desktop/오티 자동화/outputs/02_deep_analysis"
    }
  ]
}