{
  "job_id": "20260326_104322_1-yf_ot",
  "step": "antigravity_process",
  "started_at": "2026-03-26T01:43:28.572737+00:00",
  "finished_at": "2026-03-26T01:43:28.609274+00:00",
  "command": "python3 scripts/antigravity_bridge.py process --task \"/Users/kk/Desktop/오티 자동화/state/processing/20260326_104322_1-yf_ot.json\" --job-id \"20260326_104322_1-yf_ot\"",
  "returncode": 0,
  "stdout": "[Bridge] Task 20260326_104322_1-yf_ot received at /Users/kk/Desktop/오티 자동화/state/processing/20260326_104322_1-yf_ot.json\n[Bridge] Created 20260326_104322_1-yf_ot_summary.md\n[Bridge] Created 20260326_104322_1-yf_ot_questions.md\n[Bridge] Created 20260326_104322_1-yf_ot_research.md\n[Bridge] Created 20260326_104322_1-yf_ot_solutions.md\n",
  "stderr": ""
}